MANIFEST.in
README.txt
setup.py
collective/__init__.py
collective.markitup.egg-info/PKG-INFO
collective.markitup.egg-info/SOURCES.txt
collective.markitup.egg-info/dependency_links.txt
collective.markitup.egg-info/entry_points.txt
collective.markitup.egg-info/namespace_packages.txt
collective.markitup.egg-info/not-zip-safe
collective.markitup.egg-info/requires.txt
collective.markitup.egg-info/top_level.txt
collective/markitup/__init__.py
collective/markitup/configure.zcml
collective/markitup/setuphandlers.py
collective/markitup/tests.py
collective/markitup/upgrades.py
collective/markitup/upgrades.zcml
collective/markitup/version.txt
collective/markitup/browser/__init__.py
collective/markitup/browser/configure.zcml
collective/markitup/browser/finder.py
collective/markitup/browser/json.py
collective/markitup/browser/preview.pt
collective/markitup/browser/preview.py
collective/markitup/browser/redirect.py
collective/markitup/profiles/default/cssregistry.xml
collective/markitup/profiles/default/jsregistry.xml
collective/markitup/profiles/default/kssregistry.xml
collective/markitup/profiles/default/metadata.xml
collective/markitup/profiles/default/propertiestool.xml
collective/markitup/profiles/default/registry.xml
collective/markitup/profiles/uninstall/import_steps.xml
collective/markitup/profiles/uninstall/propertiestool.xml
collective/markitup/static/CHANGELOG.md
collective/markitup/static/README.md
collective/markitup/static/index.html
collective/markitup/static/init.js
collective/markitup/static/preview_styler.js
collective/markitup/static/set.js
collective/markitup/static/html/readme.txt
collective/markitup/static/html/set.js
collective/markitup/static/html/style.css
collective/markitup/static/html/images/bold.png
collective/markitup/static/html/images/clean.png
collective/markitup/static/html/images/h1.png
collective/markitup/static/html/images/h2.png
collective/markitup/static/html/images/h3.png
collective/markitup/static/html/images/h4.png
collective/markitup/static/html/images/h5.png
collective/markitup/static/html/images/h6.png
collective/markitup/static/html/images/image.png
collective/markitup/static/html/images/italic.png
collective/markitup/static/html/images/link.png
collective/markitup/static/html/images/list-bullet.png
collective/markitup/static/html/images/list-item.png
