Metadata-Version: 1.1
Name: collective.markitup
Version: 0.2
Summary: collective.markitup integrates MarkItUp with Plone
Home-page: http://smith-li.com
Author: Michael A. Smith
Author-email: michael@smith-li.com
License: MIT
Keywords: web zope plone editor
Platform: UNKNOWN
Classifier: Framework :: Plone
Classifier: Programming Language :: Python
Classifier: Programming Language :: JavaScript
Classifier: Topic :: Software Development :: Libraries :: Python Modules
Classifier: Topic :: Text Processing :: Markup
